{
  "name": "Goldenseal",
  "slug": "goldenseal",
  "summary": "Internal cross-linking supports Goldenseal through compounds such as berberine, hydrastine.",
  "description": "Internal cross-linking supports Goldenseal through compounds such as berberine, hydrastine.",
  "primaryActions": [
    "anti-inflammatory"
  ],
  "mechanisms": [
    "Inflammatory Signaling Modulation",
    "Mitochondrial Support",
    "AMPK Signaling",
    "NF-kB Modulation"
  ],
  "activeCompounds": [],
  "safetyNotes": "Generally well tolerated for most users.",
  "contraindications": [
    "Pregnancy/breastfeeding",
    "infants/newborns",
    "complex medication regimens without clinician review"
  ],
  "interactions": [
    "Potential CYP3A4/CYP2D6/P-gp interactions",
    "caution with cyclosporine",
    "tacrolimus",
    "antidiabetics",
    "anticoagulants",
    "and many drugs."
  ],
  "preparation": "",
  "traditionalUses": [],
  "evidenceLevel": "",
  "relatedHerbs": [],
  "region": "",
  "sources": [
    {
      "pubmedId": "28762712",
      "title": "Common Herbal Dietary Supplement-Drug Interactions",
      "authors": "Asher GN et al.",
      "year": 2017,
      "url": "https://pubmed.ncbi.nlm.nih.gov/28762712/"
    },
    {
      "pubmedId": "27671811",
      "title": "Berberine and Its Role in Chronic Disease",
      "authors": "Cicero AF et al.",
      "year": 2016,
      "url": "https://pubmed.ncbi.nlm.nih.gov/27671811/"
    },
    {
      "pubmedId": "33242239",
      "title": "Berberine",
      "authors": "PubMed indexed authors",
      "year": 2012,
      "url": "https://pubmed.ncbi.nlm.nih.gov/33242239/"
    }
  ],
  "governance": {
    "reviewStatus": "approved",
    "legalRisk": "none",
    "medicalRisk": "low",
    "monetizationAllowed": true,
    "indexingAllowed": false,
    "recommendationAllowed": true,
    "requiresHumanReview": false,
    "reason": ""
  },
  "evidence": {
    "reviewStatus": "sourced",
    "sourceCount": 3,
    "sourceIds": [
      "27671811",
      "28762712",
      "33242239"
    ]
  },
  "claimMap": [],
  "dosage": "Preparation-specific; use standardized product label for Root/rhizome powder and require source-backed dosage review before therapeutic claims.",
  "typical_dosage": "Preparation-specific; use standardized product label for Root/rhizome powder and require source-backed dosage review before therapeutic claims."
}
