{
  "name": "Myristica Fragrans",
  "slug": "myristica-fragrans",
  "summary": "Myristica fragrans contains Elemicin and is linked here to monoamine oxidase inhibition.",
  "description": "Myristica fragrans contains Elemicin and is linked here to monoamine oxidase inhibition.",
  "primaryActions": [
    "digestive",
    "sedative"
  ],
  "mechanisms": [
    "Neurotransmitter Modulation"
  ],
  "activeCompounds": [],
  "safetyNotes": "Generally well tolerated for most users.",
  "contraindications": [
    "pregnancy/breastfeeding without clinician supervision",
    "known allergy to the plant/family"
  ],
  "interactions": [
    "Potential interaction concern with antihypertensives/diuretics",
    "sedatives/CNS depressants",
    "use clinician review for high-dose extracts or chronic use."
  ],
  "preparation": "",
  "traditionalUses": [],
  "evidenceLevel": "",
  "relatedHerbs": [],
  "region": "",
  "sources": [
    {
      "pubmedId": "35567294",
      "title": "Nutmeg (Myristica fragrans Houtt.) essential oil: A review on its composition, biological, and pharmacological activities",
      "authors": "Ashokkumar K et al.",
      "year": 2022,
      "url": "https://pubmed.ncbi.nlm.nih.gov/35567294/"
    },
    {
      "pubmedId": "30000898",
      "title": "Nutmeg",
      "authors": "PubMed indexed authors",
      "year": 2006,
      "url": "https://pubmed.ncbi.nlm.nih.gov/30000898/"
    },
    {
      "pubmedId": "33206347",
      "title": "Phytochemical and pharmacological properties of Myristica fragrans Houtt.: an updated review",
      "authors": "Ha MT et al.",
      "year": 2020,
      "url": "https://pubmed.ncbi.nlm.nih.gov/33206347/"
    }
  ]
}
