{"@context":"https://schema.org","@graph":[{"@id":"https://thehippiescientist.net/herbs/cranberry/#entity","@type":["MedicalSubstance","Thing"],"additionalProperty":[{"@type":"PropertyValue","propertyID":"evidence tier","value":"Moderate Human Evidence"},{"@type":"PropertyValue","propertyID":"evidence label","value":"b"},{"@type":"PropertyValue","propertyID":"AI entity completeness score","value":21}],"description":"Cranberry (Vaccinium macrocarpon) botanical profile with evidence, safety, and practical fit.","identifier":[{"@type":"PropertyValue","propertyID":"THS entity id","value":"ths:herb:cranberry"},{"@type":"PropertyValue","propertyID":"THS slug","value":"cranberry"}],"name":"Cranberry (Vaccinium macrocarpon)","subjectOf":{"@id":"https://thehippiescientist.net/herbs/cranberry/#evidence-data"},"url":"https://thehippiescientist.net/herbs/cranberry/"},{"@id":"https://thehippiescientist.net/herbs/cranberry/#evidence-data","@type":"Article","about":{"@id":"https://thehippiescientist.net/herbs/cranberry/#entity"},"author":{"@type":"Organization","name":"The Hippie Scientist","url":"https://thehippiescientist.net"},"description":"Cranberry (Vaccinium macrocarpon) botanical profile with evidence, safety, and practical fit.","headline":"Cranberry (Vaccinium macrocarpon) evidence, safety, and entity data","mainEntity":{"@id":"https://thehippiescientist.net/herbs/cranberry/#entity"},"publisher":{"@type":"Organization","name":"The Hippie Scientist","url":"https://thehippiescientist.net"},"url":"https://thehippiescientist.net/herbs/cranberry/"}]}
