{"@context":"https://schema.org","@graph":[{"@id":"https://thehippiescientist.net/herbs/schisandra-berry/#entity","@type":["MedicalSubstance","Thing"],"additionalProperty":[{"@type":"PropertyValue","propertyID":"evidence tier","value":"Limited Human Evidence"},{"@type":"PropertyValue","propertyID":"evidence label","value":"c"},{"@type":"PropertyValue","propertyID":"AI entity completeness score","value":21}],"description":"It is best framed specifically around berry lignans and traditional stress-support positioning.","identifier":[{"@type":"PropertyValue","propertyID":"THS entity id","value":"ths:herb:schisandra-berry"},{"@type":"PropertyValue","propertyID":"THS slug","value":"schisandra-berry"}],"name":"Schisandra Berry","subjectOf":{"@id":"https://thehippiescientist.net/herbs/schisandra-berry/#evidence-data"},"url":"https://thehippiescientist.net/herbs/schisandra-berry/"},{"@id":"https://thehippiescientist.net/herbs/schisandra-berry/#evidence-data","@type":"Article","about":{"@id":"https://thehippiescientist.net/herbs/schisandra-berry/#entity"},"author":{"@type":"Organization","name":"The Hippie Scientist","url":"https://thehippiescientist.net"},"description":"It is best framed specifically around berry lignans and traditional stress-support positioning.","headline":"Schisandra Berry evidence, safety, and entity data","mainEntity":{"@id":"https://thehippiescientist.net/herbs/schisandra-berry/#entity"},"publisher":{"@type":"Organization","name":"The Hippie Scientist","url":"https://thehippiescientist.net"},"url":"https://thehippiescientist.net/herbs/schisandra-berry/"}]}
