{
  "id": "pregnenolone",
  "slug": "pregnenolone",
  "name": "Pregnenolone",
  "summary": "Pregnenolone is a neurosteroid precursor with limited human trial evidence in mood, substance-use, and psychiatric contexts; it should be framed as experimental rather than a general cognition or hormone-optimization supplement.",
  "description": "Pregnenolone is a neurosteroid precursor with limited human trial evidence in mood, substance-use, and psychiatric contexts; it should be framed as experimental rather than a general cognition or hormone-optimization supplement.",
  "compoundClass": "",
  "mechanisms": [
    "Neurotransmitter Modulation",
    "Hormonal Signaling Context"
  ],
  "targets": [],
  "pathways": [],
  "foundIn": [],
  "bioavailability": "",
  "safetyNotes": "Generally well tolerated for most users.",
  "evidenceLevel": "",
  "relatedCompounds": []
}
