{
  "id": "pycnogenol",
  "slug": "pycnogenol",
  "name": "Pycnogenol",
  "summary": "Improves endothelial function and reduces blood pressure.",
  "description": "Improves endothelial function and reduces blood pressure.",
  "compoundClass": "",
  "mechanisms": [
    "Oxidative Stress Modulation",
    "Vascular Function Support",
    "Endothelial Function Support",
    "Endothelial Function",
    "Oxidative Stress"
  ],
  "targets": [],
  "pathways": [],
  "foundIn": [],
  "bioavailability": "",
  "safetyNotes": "Generally well tolerated for most users.",
  "evidenceLevel": "",
  "relatedCompounds": [],
  "governance": {
    "reviewStatus": "approved",
    "legalRisk": "none",
    "medicalRisk": "low",
    "monetizationAllowed": true,
    "indexingAllowed": true,
    "recommendationAllowed": true,
    "requiresHumanReview": false,
    "reason": ""
  },
  "evidence": {
    "reviewStatus": "sourced",
    "sourceCount": 3,
    "sourceIds": [
      "claim:study-row-148",
      "https://pubmed.ncbi.nlm.nih.gov/31763928/ | https://pubmed.ncbi.nlm.nih.gov/18037769/",
      "pmid:31763928"
    ]
  },
  "claimMap": [],
  "indexability_status": "PUBLISH",
  "robots": "index,follow",
  "effects": [
    "Cardiovascular Health",
    "Oxidative Stress",
    "Stress Response",
    "Metabolic Health",
    "Exercise Performance"
  ],
  "primary_effects": [
    "Cardiovascular Health",
    "Oxidative Stress",
    "Stress Response",
    "Metabolic Health",
    "Exercise Performance"
  ],
  "raw_mechanisms": [
    "Oxidative Stress Modulation",
    "Vascular Function Support",
    "Endothelial Function Support",
    "Endothelial Function",
    "Oxidative Stress"
  ],
  "canonical_mechanisms": [
    "Antioxidant",
    "Vascular function support",
    "Nitric oxide modulation"
  ],
  "mechanism_categories": [
    "core",
    "cardiovascular"
  ],
  "mechanism_classes": [
    "Physiological effect",
    "Signaling molecule modulation"
  ],
  "mechanism_target_systems": [],
  "mechanism_normalization_status": "partially_mapped",
  "unmapped_mechanisms": [
    "Endothelial Function",
    "Oxidative Stress"
  ],
  "evidence_tier": "Mechanistic Evidence",
  "profile_status": "commercial_ready",
  "runtime_export_decision": "full_public_runtime",
  "sitemap_included": true,
  "indexability_score": 85,
  "indexability_reasons": [
    "effect-coverage",
    "evidence-signal",
    "export-decision:full_public_runtime",
    "identity-present",
    "mechanism-context",
    "profile-status:commercial_ready",
    "safety-context-missing",
    "summary-present",
    "summary-quality-missing"
  ],
  "safety": "Generally well tolerated for most users."
}
