{
  "slug": "electrolytes-magnesium-blend",
  "name": "Electrolytes - Magnesium Blend",
  "summary": "Magnesium blends support deficiency correction and neuromuscular function, but cramp evidence is mixed.",
  "description": "Blend of magnesium salts used for electrolyte and deficiency contexts.",
  "effects": [
    "electrolytes",
    "hydration"
  ],
  "primary_effects": [
    "electrolytes",
    "hydration"
  ],
  "mechanisms": [
    "Mitochondrial Support",
    "Metabolic Regulation"
  ],
  "raw_mechanisms": [
    "Mitochondrial Support",
    "Metabolic Regulation"
  ],
  "canonical_mechanisms": [
    "Mitochondrial biogenesis",
    "Metabolic regulation"
  ],
  "mechanism_categories": [
    "mitochondrial",
    "core"
  ],
  "mechanism_classes": [
    "Physiological/cellular effect",
    "Physiological effect"
  ],
  "mechanism_target_systems": [
    "mitochondrial",
    "metabolic"
  ],
  "mechanism_normalization_status": "fully_mapped",
  "unmapped_mechanisms": [],
  "evidence_grade": "b",
  "evidence_tier": "Moderate Human Evidence",
  "contraindications": [
    "Avoid high-dose magnesium with kidney disease",
    "separate from thyroid medication",
    "bisphosphonates",
    "and some antibiotics"
  ],
  "interactions": [],
  "side_effects": [],
  "dosage": "200-400",
  "typical_dosage": "200-400",
  "forms": [],
  "available_forms": [],
  "conditions": [
    "Low-priority hydration support when sodium/potassium amounts are transparent"
  ],
  "tags": [],
  "keywords": [],
  "affiliate_ready": false,
  "affiliate_url": "https://www.amazon.com/s?k=electrolytes-magnesium-blend+supplement&tag=razzleberry02-20",
  "affiliate_label": "Check sourcing options",
  "affiliate_query": "Electrolytes - Magnesium Blend supplement powder",
  "default_product_type": "",
  "amazon_affiliate_url": "",
  "iherb_affiliate_url": "",
  "buying_criteria": [
    "Glycinate for sleep/anxiety or threonate for cognition",
    "elemental magnesium dose clearly listed",
    "avoid oxide-first products for sleep/anxiety"
  ],
  "doNotMonetize": false,
  "doNotPromote": false,
  "governance_status": "",
  "legal_status": "",
  "controlled_status": "",
  "controlled_schedule": "",
  "dea_status": "",
  "dea_watchlist_status": "",
  "regulatory_status": "",
  "profile_status": "commercial_ready",
  "runtime_export_decision": "primary_runtime_priority",
  "visibility_tier": "public",
  "robots": "index,follow",
  "sitemap_included": true,
  "indexability_status": "eligible",
  "indexability_score": {
    "status": "PUBLISH",
    "score": 100,
    "robots": "index,follow",
    "sitemap_included": true,
    "reasons": [
      "effect-coverage",
      "evidence-signal",
      "export-decision:primary_runtime_priority",
      "identity-present",
      "mechanism-context",
      "profile-status:commercial_ready",
      "safety-context",
      "summary-depth",
      "summary-quality-missing"
    ]
  },
  "indexability_reasons": [],
  "meta_title": "",
  "meta_description": "",
  "featured": false,
  "controlled_substance": false
}
