{"@context":"https://schema.org","@graph":[{"@id":"https://thehippiescientist.net/compounds/11-keto-beta-boswellic-acid/#entity","@type":["ChemicalSubstance","MolecularEntity"],"additionalProperty":[{"@type":"PropertyValue","propertyID":"evidence tier","value":"Limited Human Evidence"},{"@type":"PropertyValue","propertyID":"evidence label","value":"c"},{"@type":"PropertyValue","propertyID":"AI entity completeness score","value":18}],"description":"Keto-boswellic acid associated with 5-LOX-related signaling and inflammatory modulation.","identifier":[{"@type":"PropertyValue","propertyID":"THS entity id","value":"ths:compound:11-keto-beta-boswellic-acid"},{"@type":"PropertyValue","propertyID":"THS slug","value":"11-keto-beta-boswellic-acid"}],"name":"11-keto-beta-boswellic acid","subjectOf":{"@id":"https://thehippiescientist.net/compounds/11-keto-beta-boswellic-acid/#evidence-data"},"url":"https://thehippiescientist.net/compounds/11-keto-beta-boswellic-acid/"},{"@id":"https://thehippiescientist.net/compounds/11-keto-beta-boswellic-acid/#evidence-data","@type":"Article","about":{"@id":"https://thehippiescientist.net/compounds/11-keto-beta-boswellic-acid/#entity"},"author":{"@type":"Organization","name":"The Hippie Scientist","url":"https://thehippiescientist.net"},"description":"Keto-boswellic acid associated with 5-LOX-related signaling and inflammatory modulation.","headline":"11-keto-beta-boswellic acid evidence, safety, and entity data","mainEntity":{"@id":"https://thehippiescientist.net/compounds/11-keto-beta-boswellic-acid/#entity"},"publisher":{"@type":"Organization","name":"The Hippie Scientist","url":"https://thehippiescientist.net"},"url":"https://thehippiescientist.net/compounds/11-keto-beta-boswellic-acid/"}]}
