{"@context":"https://schema.org","@graph":[{"@id":"https://thehippiescientist.net/compounds/bacopaside-ii/#entity","@type":["ChemicalSubstance","MolecularEntity"],"additionalProperty":[{"@type":"PropertyValue","propertyID":"evidence tier","value":"Moderate Human Evidence"},{"@type":"PropertyValue","propertyID":"evidence label","value":"c"},{"@type":"PropertyValue","propertyID":"AI entity completeness score","value":17}],"description":"Bacopa triterpenoid saponin associated with nootropic activity and kinase-linked neuroprotective signaling.","identifier":[{"@type":"PropertyValue","propertyID":"THS entity id","value":"ths:compound:bacopaside-ii"},{"@type":"PropertyValue","propertyID":"THS slug","value":"bacopaside-ii"}],"name":"bacopaside ii","subjectOf":{"@id":"https://thehippiescientist.net/compounds/bacopaside-ii/#evidence-data"},"url":"https://thehippiescientist.net/compounds/bacopaside-ii/"},{"@id":"https://thehippiescientist.net/compounds/bacopaside-ii/#evidence-data","@type":"Article","about":{"@id":"https://thehippiescientist.net/compounds/bacopaside-ii/#entity"},"author":{"@type":"Organization","name":"The Hippie Scientist","url":"https://thehippiescientist.net"},"description":"Bacopa triterpenoid saponin associated with nootropic activity and kinase-linked neuroprotective signaling.","headline":"bacopaside ii evidence, safety, and entity data","mainEntity":{"@id":"https://thehippiescientist.net/compounds/bacopaside-ii/#entity"},"publisher":{"@type":"Organization","name":"The Hippie Scientist","url":"https://thehippiescientist.net"},"url":"https://thehippiescientist.net/compounds/bacopaside-ii/"}]}
