{"@context":"https://schema.org","@graph":[{"@id":"https://thehippiescientist.net/compounds/boswellic-acid/#entity","@type":["ChemicalSubstance","MolecularEntity"],"additionalProperty":[{"@type":"PropertyValue","propertyID":"evidence tier","value":"Limited Human Evidence"},{"@type":"PropertyValue","propertyID":"evidence label","value":"c"},{"@type":"PropertyValue","propertyID":"AI entity completeness score","value":17}],"description":"Pentacyclic triterpenoid boswellic acid from frankincense resin with 5-LOX and inflammatory pathway activity.","identifier":[{"@type":"PropertyValue","propertyID":"THS entity id","value":"ths:compound:boswellic-acid"},{"@type":"PropertyValue","propertyID":"THS slug","value":"boswellic-acid"}],"name":"boswellic acid","subjectOf":{"@id":"https://thehippiescientist.net/compounds/boswellic-acid/#evidence-data"},"url":"https://thehippiescientist.net/compounds/boswellic-acid/"},{"@id":"https://thehippiescientist.net/compounds/boswellic-acid/#evidence-data","@type":"Article","about":{"@id":"https://thehippiescientist.net/compounds/boswellic-acid/#entity"},"author":{"@type":"Organization","name":"The Hippie Scientist","url":"https://thehippiescientist.net"},"description":"Pentacyclic triterpenoid boswellic acid from frankincense resin with 5-LOX and inflammatory pathway activity.","headline":"boswellic acid evidence, safety, and entity data","mainEntity":{"@id":"https://thehippiescientist.net/compounds/boswellic-acid/#entity"},"publisher":{"@type":"Organization","name":"The Hippie Scientist","url":"https://thehippiescientist.net"},"url":"https://thehippiescientist.net/compounds/boswellic-acid/"}]}
