{"@context":"https://schema.org","@graph":[{"@id":"https://thehippiescientist.net/compounds/magnoflorine/#entity","@type":["ChemicalSubstance","MolecularEntity"],"additionalProperty":[{"@type":"PropertyValue","propertyID":"evidence tier","value":"Limited Human Evidence"},{"@type":"PropertyValue","propertyID":"evidence label","value":"c"},{"@type":"PropertyValue","propertyID":"AI entity completeness score","value":14}],"description":"Aporphine alkaloid reported from Coptis and lotus with AMPK and inflammatory pathway activity.","identifier":[{"@type":"PropertyValue","propertyID":"THS entity id","value":"ths:compound:magnoflorine"},{"@type":"PropertyValue","propertyID":"THS slug","value":"magnoflorine"}],"name":"magnoflorine","subjectOf":{"@id":"https://thehippiescientist.net/compounds/magnoflorine/#evidence-data"},"url":"https://thehippiescientist.net/compounds/magnoflorine/"},{"@id":"https://thehippiescientist.net/compounds/magnoflorine/#evidence-data","@type":"Article","about":{"@id":"https://thehippiescientist.net/compounds/magnoflorine/#entity"},"author":{"@type":"Organization","name":"The Hippie Scientist","url":"https://thehippiescientist.net"},"description":"Aporphine alkaloid reported from Coptis and lotus with AMPK and inflammatory pathway activity.","headline":"magnoflorine evidence, safety, and entity data","mainEntity":{"@id":"https://thehippiescientist.net/compounds/magnoflorine/#entity"},"publisher":{"@type":"Organization","name":"The Hippie Scientist","url":"https://thehippiescientist.net"},"url":"https://thehippiescientist.net/compounds/magnoflorine/"}]}
