{
  "slug": "garcinia-mangostana",
  "name": "Garcinia Mangostana",
  "summary": "Garcinia mangostana contains Mangostin and is linked here to NF-κB inhibition.",
  "description": "Garcinia mangostana contains Mangostin and is linked here to NF-κB inhibition.",
  "effects": [
    "antioxidant",
    "anti-inflammatory"
  ],
  "primary_effects": [
    "antioxidant",
    "anti-inflammatory"
  ],
  "mechanisms": [
    "Inflammatory Signaling Modulation",
    "Oxidative Stress Modulation",
    "NF-kB Modulation"
  ],
  "raw_mechanisms": [
    "Inflammatory Signaling Modulation",
    "Oxidative Stress Modulation",
    "NF-kB Modulation"
  ],
  "canonical_mechanisms": [
    "Anti-inflammatory",
    "Antioxidant",
    "NF-kB inhibition"
  ],
  "mechanism_categories": [
    "core",
    "inflammatory"
  ],
  "mechanism_classes": [
    "Physiological effect",
    "Signaling pathway modulation"
  ],
  "mechanism_target_systems": [
    "immune/inflammatory",
    "redox/mitochondrial"
  ],
  "mechanism_normalization_status": "fully_mapped",
  "unmapped_mechanisms": [],
  "evidence_grade": "c",
  "evidence_tier": "Limited Human Evidence",
  "contraindications": [
    "Pregnancy/breastfeeding without clinician guidance",
    "bleeding disorder/anticoagulant use without review"
  ],
  "interactions": [
    "Theoretical anticoagulant/antiplatelet interactions",
    "product-specific evidence limited."
  ],
  "side_effects": [],
  "dosage": "",
  "typical_dosage": "",
  "forms": [],
  "available_forms": [],
  "conditions": [],
  "tags": [],
  "keywords": [],
  "affiliate_ready": false,
  "affiliate_url": "https://www.amazon.com/s?k=organic+garcinia-mangostana&tag=razzleberry02-20",
  "affiliate_label": "Check sourcing options",
  "affiliate_query": "garcinia mangostana capsule, tea, or standardized extract supplement",
  "default_product_type": "",
  "amazon_affiliate_url": "",
  "iherb_affiliate_url": "",
  "buying_criteria": [
    "clear labeled dose",
    "active marker or extract ratio disclosed",
    "third-party testing",
    "avoid if listed contraindications apply"
  ],
  "doNotMonetize": false,
  "doNotPromote": false,
  "governance_status": "",
  "legal_status": "",
  "controlled_status": "",
  "controlled_schedule": "",
  "dea_status": "",
  "dea_watchlist_status": "",
  "regulatory_status": "",
  "profile_status": "partial",
  "runtime_export_decision": "limited",
  "visibility_tier": "public",
  "robots": "index,follow",
  "sitemap_included": true,
  "indexability_status": "eligible",
  "indexability_score": {
    "status": "PUBLISH",
    "score": 83,
    "robots": "index,follow",
    "sitemap_included": true,
    "reasons": [
      "effect-coverage",
      "evidence-signal",
      "export-decision:limited",
      "identity-present",
      "mechanism-context",
      "profile-status:partial",
      "safety-context",
      "summary-present",
      "summary-quality-missing"
    ]
  },
  "indexability_reasons": [],
  "meta_title": "",
  "meta_description": "",
  "featured": false,
  "controlled_substance": false,
  "sources": [
    {
      "pubmedId": "40321800",
      "title": "Mechanistic Insights into the Anti-Glioma Effects of Exosome-Like Nanoparticles Derived from Garcinia Mangostana L.: A Metabolomics, Network Pharmacology, and Experimental Study",
      "authors": "Luo X et al.",
      "year": 2025,
      "url": "https://pubmed.ncbi.nlm.nih.gov/40321800/"
    },
    {
      "pubmedId": "36937066",
      "title": "The origin of cultivated mangosteen (Garcinia mangostana L. var. mangostana): Critical assessments and an evolutionary-ecological perspective",
      "authors": "Yao TL et al.",
      "year": 2023,
      "url": "https://pubmed.ncbi.nlm.nih.gov/36937066/"
    },
    {
      "pubmedId": "32280205",
      "title": "Nanoparticle Drug Delivery Systems for α-Mangostin",
      "authors": "Wathoni N et al.",
      "year": 2020,
      "url": "https://pubmed.ncbi.nlm.nih.gov/32280205/"
    }
  ]
}
